sqs_queue/__init__.py
sqs_queue/interfaces.py
sqs_queue/main.py
sqs_queue_package_ya-0.0.4.dist-info/LICENSE
sqs_queue_package_ya-0.0.4.dist-info/METADATA
sqs_queue_package_ya-0.0.4.dist-info/WHEEL
sqs_queue_package_ya-0.0.4.dist-info/top_level.txt
sqs_queue_package_ya-0.0.4.dist-info/RECORD
