Metadata-Version: 2.1
Name: sqs_queue_package_ya
Version: 0.0.4
Summary: Sqs queue
Home-page: https://gitlab.com/savarety/sqs-queue/-/tree/test?ref_type=heads
Author: Nick Jaraf
Author-email: savarety.dev@gmail.com
Classifier: Programming Language :: Python :: 3.8
Classifier: License :: OSI Approved :: MIT License
Classifier: Operating System :: OS Independent
Requires-Python: >=3.6
License-File: LICENSE
